panapi/__init__.py
panapi/config/__init__.py
panapi/config/identity.py
panapi/config/management.py
panapi/config/network.py
panapi/config/objects.py
panapi/config/security.py
panapi-0.0.1.dist-info/LICENSE
panapi-0.0.1.dist-info/METADATA
panapi-0.0.1.dist-info/WHEEL
panapi-0.0.1.dist-info/top_level.txt
panapi-0.0.1.dist-info/RECORD
