Metadata-Version: 2.1
Name: panapi
Version: 0.0.1
Summary: A lightweight SDK for the Panorama Cloud API
Home-page: https://github.com/PaloAltoNetworks/panapi
Author: Palo Alto Networks
Author-email: devrel@paloaltonetworks.com
Classifier: Development Status :: 3 - Alpha
Classifier: Intended Audience :: Developers
Classifier: Programming Language :: Python :: 3.6
Classifier: Programming Language :: Python :: 3.7
Classifier: Programming Language :: Python :: 3.8
Classifier: License :: OSI Approved :: ISC License (ISCL)
Classifier: Natural Language :: English
Requires-Python: >=3.6
License-File: LICENSE
Requires-Dist: certifi (==2022.6.15)
Requires-Dist: cffi (==1.15.1)
Requires-Dist: charset-normalizer (==2.1.1)
Requires-Dist: cryptography (==37.0.4)
Requires-Dist: idna (==3.3)
Requires-Dist: oauthlib (==3.2.0)
Requires-Dist: pycparser (==2.21)
Requires-Dist: PyJWT (==2.4.0)
Requires-Dist: PyYAML (==6.0)
Requires-Dist: requests (==2.28.1)
Requires-Dist: requests-oauthlib (==1.3.1)
Requires-Dist: urllib3 (==1.26.12)
